postmaniac/__init__.py
postmaniac/postmaniac.py
postmaniac-1.0.0.dist-info/METADATA
postmaniac-1.0.0.dist-info/WHEEL
postmaniac-1.0.0.dist-info/entry_points.txt
postmaniac-1.0.0.dist-info/licenses/LICENSE.md
postmaniac-1.0.0.dist-info/RECORD
