Metadata-Version: 2.4
Name: postmaniac
Version: 1.0.0
Summary: Postman OSINT tool to extract creds, token, username, email & more from Postman Public Workspaces.
Project-URL: Homepage, https://github.com/boringthegod/postmaniac
Project-URL: Bug Tracker, https://github.com/boringthegod/postmaniac/issues
Author-email: Pierre Ceberio <boringthegod@tutanota.com>
License-File: LICENSE.md
Keywords: cybersecurity,investigation,lespireshat,osint,pentest,postman
Requires-Python: >=3.0
Requires-Dist: requests
Requires-Dist: rich
